shmarql/__init__.py
shmarql/__main__.py
shmarql/am.py
shmarql/biki.py
shmarql/charts.py
shmarql/config.py
shmarql/fragments.py
shmarql/layout.py
shmarql/main.py
shmarql/markdownplugin.py
shmarql/px_util.py
shmarql/qry.py
shmarql-0.64.dist-info/licenses/LICENSE
shmarql-0.64.dist-info/METADATA
shmarql-0.64.dist-info/WHEEL
shmarql-0.64.dist-info/entry_points.txt
shmarql-0.64.dist-info/top_level.txt
shmarql-0.64.dist-info/RECORD
