Metadata-Version: 2.4
Name: shmarql
Version: 0.64
Summary: A Linked Data publishing platform for semantic web professionals in a hurry.
Author-email: Etienne Posthumus <ep@epoz.org>
License-Expression: MIT
Project-URL: Homepage, https://shmarql.com/
Project-URL: Repository, https://github.com/epoz/shmarql
Keywords: SPARQL,search,RDF,Linked Data
Requires-Python: >=3.10
License-File: LICENSE
Requires-Dist: apsw==3.50.3.0
Requires-Dist: bcrypt==3.2.0
Requires-Dist: fizzysearch==0.31
Requires-Dist: markdown>=3.9
Requires-Dist: mkdocs-material>=9.6.21
Requires-Dist: monsterui>=1.0.29
Requires-Dist: pandas>=2.3.3
Requires-Dist: passlib>=1.7.4
Requires-Dist: plotly>=6.3.1
Requires-Dist: pygments>=2.19.2
Requires-Dist: pyoxigraph>=0.5.0
Requires-Dist: python-fasthtml>=0.12.29
Requires-Dist: rdflib>=7.2.1
Requires-Dist: tree-sitter-sparql==0.1.0
Dynamic: license-file
